pytest_unique/__init__.py
pytest_unique/count.py
pytest_unique/fixtures.py
pytest_unique/lock.py
pytest_unique/registry.py
pytest_unique/unique.py
pytest_unique-0.1.7.dist-info/LICENSE.rst
pytest_unique-0.1.7.dist-info/METADATA
pytest_unique-0.1.7.dist-info/WHEEL
pytest_unique-0.1.7.dist-info/entry_points.txt
pytest_unique-0.1.7.dist-info/RECORD
