Metadata-Version: 2.3
Name: pytest-unique
Version: 0.1.7
Summary: Pytest fixture to generate unique values.
Author: Marc Tardif
Author-email: marc@interunion.ca
Requires-Python: >=3.10,<4.0
Classifier: Programming Language :: Python :: 3
Classifier: Programming Language :: Python :: 3.10
Classifier: Programming Language :: Python :: 3.11
Classifier: Programming Language :: Python :: 3.12
Classifier: Programming Language :: Python :: 3.13
Requires-Dist: attrs (>=25.3.0,<26.0.0)
Requires-Dist: pytest (>=9.0.0,<10.0.0)
